wandalib/__init__.py
wandalib/high_level.py
wandalib/py.typed
wandalib/utils.py
wandalib/get_data/__init__.py
wandalib/get_data/get_data.py
wandalib/graph_data/__init__.py
wandalib/graph_data/graph.py
wandalib/partial_works/__init__.py
wandalib/partial_works/other.py
wandalib-0.1.1.dist-info/METADATA
wandalib-0.1.1.dist-info/WHEEL
wandalib-0.1.1.dist-info/RECORD
