Metadata-Version: 2.4
Name: wandalib
Version: 0.1.1
Summary: Add your description here
Author-email: Juan David <juanguerrero09mc@gmail.com>
Maintainer-email: Juan David <juanguerrero09mc@gmail.com>
Requires-Python: >=3.9
Requires-Dist: matplotlib>=3.9.4
Requires-Dist: numpy>=2.0.2
Requires-Dist: pandas>=2.2.3
Requires-Dist: python-dotenv>=1.0.1
Requires-Dist: pywanda==4.7.0a2
Requires-Dist: setuptools>=75.8.0
Requires-Dist: twine>=6.1.0
Requires-Dist: wheel>=0.45.1
